{
    "networkId": 31,
    "plazaId": 15,
    "staffId": "00111",
    "bagNumber": "2",
    "safetyBeltNumber": "2",
    "shiftTypeId": 1,
    "declareDateTime": "2021-02-05T11:07:10.079+07:00",
    "attendanceDateTime": "2021-02-05T11:07:17.684+07:00",
    "departureDateTime": "2021-02-05T11:07:28.019+07:00",
    "operationDate": "2021-02-05T00:00:00.000+07:00",
    "declareById": "00111",
    "declareByName": "อนุสรน์สถาน",
    "cashTotalAmount": 0,
    "couponTotalAmount": 0,
    "couponBookTotalAmount": 0,
    "cardAllowTotalAmount": 0,
    "qrcodeTotalAmount": 10,
    "emvTotalAmount": 10,
    "otherTotalAmount": 0,
    "cashRemark": "",
    "otherRemark": "",
    "chiefId": "00444",
    "chiefName": "Mr. CTC Test",
    "jobList": [
        {
            "networkId": 31,
            "plazaId": 15,
            "laneId": 3,
            "jobNo": 3,
            "staffId": "00111",
            "bojDateTime": "2021-02-02T19:52:44.450+07:00",
            "eojDateTime": "2021-02-02T19:53:49.617+07:00"
        },
        {
            "networkId": 31,
            "plazaId": 16,
            "laneId": 12,
            "jobNo": 7,
            "staffId": "00111",
            "bojDateTime": "2021-02-02T19:53:56.393+07:00",
            "eojDateTime": "2021-02-02T19:54:05.695+07:00"
        }
    ],
    "cashList": [],
    "couponList": [],
    "couponBookList": [],
    "cardAllowList": [],
    "qrcodeList": [
        {
            "approvalCode": "APV-5Z-26892",
            "trxDate": "2021-02-02T19:53:13.102+07:00",
            "amount": 3
        },
        {
            "approvalCode": "APV-NS-90914",
            "trxDate": "2021-02-02T19:54:04.338+07:00",
            "amount": 7
        }
    ],
    "emvList": [
        {
            "approvalCode": "APV-48-84900",
            "trxDate": "2021-02-02T19:53:10.151+07:00",
            "amount": 3
        },
        {
            "approvalCode": "APV-QK-83367",
            "trxDate": "2021-02-02T19:54:00.997+07:00",
            "amount": 7
        }
    ]
}