{
    "list": [
        {
            "networkId": 31,
            "plazaId": 15,
            "laneId": 2,
            "jobNo": 1,
            "staffId": "00444",
            "bojDateTime": "2021-06-04T13:02:06.149+0700",
            "eojDateTime": "2021-06-04T13:02:07.635+0700"
        },
        {
            "networkId": 31,
            "plazaId": 15,
            "laneId": 1,
            "jobNo": 2,
            "staffId": "20001",
            "bojDateTime": "2021-06-04T13:03:34.682+0700",
            "eojDateTime": "2021-06-04T13:03:35.799+0700"
        }
    ],
    "status": {
        "code": "S200",
        "message": "Success"
    }
}